{"company_info": {"Company Description": "About Us- Unique Travelite Services Pvt. Ltd.UTS Is An ISO Certified Entity Listed On Ministry Of Corporate Affairs. Our Company Provides Best-In-Class Service In The Travel &amp; Tourism Sector Across World", "Email": "salma.uts@gmail.com", "Company Name": "Freelancer Mohan Shyam", "Telephone": "9867465254"}, "api_data": {"job_location": ["Noida", "Gurugram", "Faridabad", "Mumbai City", "Delhi"], "jd_id": "7128611", "job_keywords": ["mcad.net", " msc-s", " geography", "digital electronics", " hr", " mass hiring", " graduation", " communication engineering", "  circuit theory", " bba", " mca", " b.tech", " hons", " computer science", " teaching", " geo"], "job_industry": "Travel / Tourism", "company_name": "Freelancer Mohan Shyam", "job_experience": "0 to 5 Yrs", "job_title": "Part Time Opportunity for Freshers And Students"}, "other_details": {"Other Skills:": ["digital electronics", "hr", "mass hiring", "graduation", "communication engineering", "circuit theory", "bba", "mca", "b.tech", "hons", "computer science", "teaching", "geo"], "Department:": ["Marketing / Communication"], "Industry:": ["Travel / Tourism"], "Skills:": ["mcad.net", "msc-s", "geography"]}, "topbox_information": {"salary_information": "Rs 3.0  - 6 Lakh/Yr"}, "jd_information": {"description": "Hello to all readers,We, At Unique Travelite Services( UTS), Are Looking For Individuals Who Can Promote Our Business (Only On Internet) In Travel &amp; Tourism (Part Time/Full Time) &amp; Provide Customer Service To People Across India.UTS Is An ISO Certified Entity Listed On Ministry Of Corporate Affairs. Our Company Provides Best-In-Class Service In The Travel &amp; Tourism Sector Across World. Besides This, UTS Envisions Providing Income Opportunity To Those People Who Are Passionate To Fulfill Their Dreams.&nbsp;We Are Offering:1. Day Shift/No Targets/No Calling/No Product Selling.&nbsp;2. Earn Huge Weekly Income (Up To 10,000)This Position Is Open For People In Service/Business/College. Even Retired/Housewives/Fresher Can Join Us.MR.Ather Hussain (HR Executive)9867465254"}, "_id": "7128611"}