{"company_info": {"Company Description": "Ways and Works Consulting LLP is Leading recruitment firm in India catering to clients across sectors.Website - www.waysandworks.com", "Email": "neha@waysandworks.com", "Company Name": "Ways and Works Consulting LLP", "Telephone": "9953328778"}, "api_data": {"job_location": ["Bhubaneswar"], "jd_id": "8045219", "job_keywords": ["css3", " svn", " c", " java", " ios", " c++", " jquery", " databases", " android", " php", "web", " objective c", " phonegap", " ionic framework", " mobile application development", " android java", " html5", " rxjs", " jquery mobile", " services", " apache cordova", " cordova", " android sdk", " iphone sdk"], "job_industry": "Travel / Tourism", "company_name": "Ways and Works Consulting LLP", "job_experience": "2 to 5 Yrs", "job_title": "Sr. Mobile Application Developer - Orrisa"}, "other_details": {"Other Skills:": ["web", "objective c", "phonegap", "ionic framework", "mobile application development", "android java", "html5", "rxjs", "jquery mobile", "services", "apache cordova", "cordova", "android sdk", "iphone sdk"], "Department:": ["Web / Mobile Technologies"], "Industry:": ["Travel / Tourism"], "Skills:": ["css3", "svn", "c", "java", "ios", "c++", "jquery", "databases", "android", "php"]}, "topbox_information": {"salary_information": "Rs 3.0  - 4.5 Lakh/Yr"}, "jd_information": {"description": "Key SkillsThorough Knowledge of Ionic Framework and Cordova/PhonegapStrong experience in building hybrid mobile application for Android and iOS using Cordovawith Ionic FrameworkExperience with Offline Storage and Databases, Push Messaging, NotificationsExperience integrating 3rd Party SDKs such as Facebook, Google, PayU, PayPal etcSolid fundamentals in PHP, HTML5, RWD, CSS3Strong experience integrating web services and Angular 2Strong experience in securing and optimising applicationsComfort in working with version control toolsMinimum of 2 to 4 years hands-on experience in developing&nbsp;mobile&nbsp;nativeand&nbsp;hybrid&nbsp;applications for Android and iOSMinimum of 2 years of experience in developing and implementing&nbsp;mobile&nbsp;applicationsand&nbsp;mobile&nbsp;UI/UXGood knowledge of&nbsp;Native&nbsp;mobile&nbsp;app&nbsp;development&nbsp;using iOS Objective C or Swift andAndroid -Java)&nbsp;Expert in&nbsp;Hybrid&nbsp;mobile&nbsp;app&nbsp;development&nbsp;using Angular2/4,&nbsp;RxJS, HTML5, CSS3 , Bootstrap,Typescript, ES6, JQuery and BackboneStrong understanding of HTTP Protocol, WebSocket, SSE, and other web technologiesExperience in&nbsp;mobile&nbsp;app&nbsp;unit testing framework , methodologies and technical know-how onE2E testingFamiliarity with security principles using SSL/TLS protocols and data encryption&nbsp;Experience in using source code management system like RTC, SVN and build tools like ant,maven, jenkins, gradle and grunt.&nbsp;Good written and verbal communication skills"}, "_id": "8045219"}