{"company_info": {"Company Description": "Cyber Flavors&nbsp;", "Company Name": "Cyber Flavors"}, "api_data": {"job_location": ["Hyderabad"], "jd_id": "8054888", "job_keywords": ["C", "   MICE sales", "p", " ate Sales ", "  Travel agent sales"], "job_industry": "Travel / Tourism", "company_name": "Cyber Flavors", "job_experience": "2 to 4 Yrs", "job_title": "Travel Trade/ Corporate Sales Manager"}, "other_details": {"Other Skills:": ["p", "ate Sales", "Travel agent sales"], "Department:": ["Sales / BD"], "Industry:": ["Travel / Tourism"], "Skills:": ["C", "MICE sales"]}, "topbox_information": {"salary_information": ""}, "jd_information": {"description": ""}, "_id": "8054888"}