{"company_info": {"Company Name": "ResBird Technologies Pvt. Ltd. (Amadeus India)"}, "api_data": {"job_location": ["Bhubaneswar"], "jd_id": "8343628", "job_keywords": ["sales presentations  ", "  business development  ", "  b2b  ", "  amadeus", ""], "job_industry": "Travel / Tourism", "company_name": "ResBird Technologies Pvt. Ltd. (Amadeus India)", "job_experience": "3 to 8 Yrs", "job_title": "opening for Executive"}, "other_details": {"Department:": ["Sales / BD"], "Industry:": ["Travel / Tourism"], "Skills:": ["sales presentations", "business development", "b2b", "amadeus"]}, "topbox_information": {"salary_information": ""}, "jd_information": {"description": ""}, "_id": "8343628"}